{
    "id": "30087/m_3008718_sw_16_1_20130805/rgb",
    "type": "Feature",
    "geometry": {
        "coordinates": [
            [
                [
                    -87.875,
                    30.625
                ],
                [
                    -87.875,
                    30.6875
                ],
                [
                    -87.8125,
                    30.6875
                ],
                [
                    -87.8125,
                    30.625
                ],
                [
                    -87.875,
                    30.625
                ]
            ]
        ],
        "type": "Polygon"
    },
    "links": [
        { "rel": "self", "href": "30087/m_3008718_sw_16_1_20130805/rgb.json" },
        { "rel": "parent", "href": "30087/m_3008718_sw_16_1_20130805.json" },
        { "rel": "asset",
          "href": "s3://aws-naip/al/2013/1m/rgb/30087/m_3008718_sw_16_1_20130805.tif",
          "product": "naip/rgb.json",
          "format": "cog" }
    ],
    "properties" : {}
}
